pySwivells/__init__.py
pySwivells/cli.py
pySwivells/iomix.py
pySwivells/accounting/__init__.py
pySwivells/accounting/cleaning.py
pySwivells/accounting/reconciliation.py
pySwivells/accounting/tags.py
pySwivells/accounting/tva.py
pyswivells-1.0.7.dist-info/METADATA
pyswivells-1.0.7.dist-info/WHEEL
pyswivells-1.0.7.dist-info/entry_points.txt
pyswivells-1.0.7.dist-info/top_level.txt
pyswivells-1.0.7.dist-info/RECORD
