Metadata-Version: 2.4
Name: pySwivells
Version: 1.0.7
Summary: python utilities for Swivells
Author-email: Arnaud Hoffmann <info@css23.fr>
License: MIT
Classifier: Programming Language :: Python :: 3
Classifier: License :: OSI Approved :: MIT License
Classifier: Operating System :: OS Independent
Requires-Python: >=3.9
Requires-Dist: numpy
Requires-Dist: pandas
Requires-Dist: openpyxl
Requires-Dist: requests
Requires-Dist: rich
Requires-Dist: fire
